digital_diffeomorphism/__init__.py
digital_diffeomorphism/cli.py
digital_diffeomorphism/core.py
digital_diffeomorphism/jacobian_calculator_torch.py
digital_diffeomorphism/non_diffeomorphic_measures.py
digital_diffeomorphism/utils.py
examples/__init__.py
examples/example_nda.py
examples/example_ndv.py
digital_diffeomorphism-1.1.1.dist-info/METADATA
digital_diffeomorphism-1.1.1.dist-info/WHEEL
digital_diffeomorphism-1.1.1.dist-info/entry_points.txt
digital_diffeomorphism-1.1.1.dist-info/top_level.txt
digital_diffeomorphism-1.1.1.dist-info/RECORD
