Metadata-Version: 2.2
Name: digital_diffeomorphism
Version: 1.1.1
Summary: Digital diffeomorphism: Non-diffeomorphic volume and non-diffeomorphic area computation
Home-page: https://github.com/yihao6/digital_diffeomorphism
Author: Yihao Liu
Author-email: yliu236@jhu.edu
License: GNU General Public License v3
Project-URL: Bug Tracker, https://github.com/yihao6/digital_diffeomorphism/issues
Keywords: registration,medical images,digital diffeomorphism
Classifier: Development Status :: 3 - Alpha
Classifier: Intended Audience :: Developers
Classifier: License :: OSI Approved :: GNU General Public License v3 (GPLv3)
Classifier: Natural Language :: English
Classifier: Programming Language :: Python :: 3
Requires-Python: >=3.7
Requires-Dist: nibabel<5,>=3
Requires-Dist: numpy<2,>=1.20
Requires-Dist: torch>=1.8
